[
	{
		"ingredient": { "type": "item", "code": "stone-*", "name": "rock", "allowedVariants": ["andesite_columnar", "andesite_porous", "andesite_weathered"] },
		"pattern": [[
			"___####___",
			"___####___",
			"___####___",
			"___####___",
			"__######__",
			"__######__",
			"__######__",
			"__######__",
			"__######__",
			"__######__"
		]],
		"name": "Stone hatchet",
		"output": { "type": "item", "code": "axehead-andesite"  }
	},
	{
		"ingredient": { "type": "item", "code": "stone-*", "name": "rock", "allowedVariants": ["basalt_columnar", "basalt_columnar_light", "basalt_porous", "basalt_weathered"] },
		"pattern": [[
			"___####___",
			"___####___",
			"___####___",
			"___####___",
			"__######__",
			"__######__",
			"__######__",
			"__######__",
			"__######__",
			"__######__"
		]],
		"name": "Stone hatchet",
		"output": { "type": "item", "code": "axehead-basalt"  }
	},
	{
		"ingredient": { "type": "item", "code": "stone-*", "name": "rock", "allowedVariants": ["granite_red", "granite_smooth", "granite_smooth_red", "granite_snowy"] },
		"pattern": [[
			"___####___",
			"___####___",
			"___####___",
			"___####___",
			"__######__",
			"__######__",
			"__######__",
			"__######__",
			"__######__",
			"__######__"
		]],
		"name": "Stone hatchet",
		"output": { "type": "item", "code": "axehead-granite"  }
	},
	{
		"ingredient": { "type": "item", "code": "stone-*", "name": "rock", "allowedVariants": ["obsidian_light", "obsidian_smooth"] },
		"pattern": [[
			"___####___",
			"___####___",
			"___####___",
			"___####___",
			"__######__",
			"__######__",
			"__######__",
			"__######__",
			"__######__",
			"__######__"
		]],
		"name": "Stone hatchet",
		"output": { "type": "item", "code": "axehead-obsidian"  }
	}
]